v3d/__init__.py
v3d/point.py
v3d/vector.py
v3d-0.0.5.dist-info/LICENSE
v3d-0.0.5.dist-info/METADATA
v3d-0.0.5.dist-info/WHEEL
v3d-0.0.5.dist-info/top_level.txt
v3d-0.0.5.dist-info/RECORD
