Metadata-Version: 2.1
Name: v3d
Version: 0.0.5
Summary: A 3D vector library for basic Vector operations.
Home-page: https://github.com/mshemuni/V3D
Author: Mohammad S.Niaei
Author-email: m.shemuni@gmail.com
License: UNKNOWN
Platform: UNKNOWN
Classifier: Programming Language :: Python :: 3
Classifier: Programming Language :: Python :: 3.6
Classifier: Programming Language :: Python :: 3.7
Classifier: License :: OSI Approved :: GNU General Public License v3 (GPLv3)
Classifier: Operating System :: OS Independent
License-File: LICENSE
